LICENSE.txt
evo_package_speak/__init__.py
evo_package_speak/automation/api.yaml
evo_package_speak/automation/entity.yaml
evo_package_speak/control/CSpeakApi.py
evo_package_speak/control/__init__.py
evo_package_speak/entity/ESpeakInput.py
evo_package_speak/entity/ESpeakMapModel.py
evo_package_speak/entity/ESpeakModel.py
evo_package_speak/entity/ESpeakOutput.py
evo_package_speak/entity/EnumSpeakGender.py
evo_package_speak/entity/__init__.py
evo_package_speak/utility/USpeakApi.py
evo_package_speak/utility/__init__.py
evo_package_speak-2024.10.22328.dist-info/LICENSE.txt
evo_package_speak-2024.10.22328.dist-info/METADATA
evo_package_speak-2024.10.22328.dist-info/WHEEL
evo_package_speak-2024.10.22328.dist-info/RECORD
